[
  {
    "id": "Andrew_Nguyen_summary_2025-05-20T06-10-39-833Z_7f65e1c2.txt",
    "candidateName": "Andrew Nguyen",
    "jobTitle": "Andrew Nguyen",
    "yearsOfExperience": 0,
    "seniorityLevel": "Not specified",
    "location": "JavaScript, TypeScript",
    "industries": [
      "Technology",
      "Software",
      "Education"
    ],
    "topSkills": [],
    "educationLevel": "Bachelor of",
    "createdAt": "2025-05-20T06:10:39.833Z",
    "filePath": "/uploads/summaries/Andrew_Nguyen_summary_2025-05-20T06-10-39-833Z_7f65e1c2.txt"
  }
]